Metadata-Version: 2.1
Name: edemdsptfeb23
Version: 0.1.0
Summary: Paquete DATA SCIENCE FEB23 EDEM
Author: Alumnos DATA SCIENCE FEB23 EDEM
License: MIT
License-File: LICENSE
